README.rst
setup.cfg
setup.py
Imgservice.egg-info/PKG-INFO
Imgservice.egg-info/SOURCES.txt
Imgservice.egg-info/dependency_links.txt
Imgservice.egg-info/not-zip-safe
Imgservice.egg-info/requires.txt
Imgservice.egg-info/top_level.txt
imgservice/__init__.py
imgservice/core.py
imgservice/storage.py
imgservice/token_serializers.py
imgservice/lib/__init__.py
imgservice/lib/config.py
imgservice/loaders/__init__.py
imgservice/loaders/http.py
imgservice/loaders/s3.py
imgservice/transforms/__init__.py
tests/__init__.py
tests/conftest.py
tests/acceptance/__init__.py
tests/acceptance/test_image_proxy.py