Metadata-Version: 1.1
Name: Imgservice
Version: 0.1
Summary: Image proxy service
Home-page: https://github.com/rshk/imgservice2
Author: Samuele Santi
Author-email: samuele.santi@reinventsoftware.io
License: BSD License
Platform: UNKNOWN
Classifier: License :: OSI Approved :: BSD License
Classifier: Programming Language :: Python :: 3.6
Classifier: Programming Language :: Python :: 3 :: Only
